imos/__init__.py
imos/embedding.py
imos/main.py
imos/memory_db.py
imos/utils.py
imos-0.1.0.dist-info/licenses/LICENSE
imos-0.1.0.dist-info/METADATA
imos-0.1.0.dist-info/WHEEL
imos-0.1.0.dist-info/entry_points.txt
imos-0.1.0.dist-info/top_level.txt
imos-0.1.0.dist-info/RECORD
