Metadata-Version: 2.4
Name: imos
Version: 0.1.0
Summary: IMOS: Memory OS for Solo Professionals - Your thoughtful local memory assistant
Home-page: https://github.com/Sumitagarwal-i/IMOS_terminal
Author: IMOS Team
Author-email: support@imos.dev
License: MIT
Project-URL: Bug Reports, https://github.com/Sumitagarwal-i/IMOS_terminal/issues
Project-URL: Source, https://github.com/Sumitagarwal-i/IMOS_terminal
Project-URL: Documentation, https://github.com/Sumitagarwal-i/IMOS_terminal#readme
Keywords: memory assistant cli productivity knowledge management ai chat
Classifier: Development Status :: 4 - Beta
Classifier: Intended Audience :: End Users/Desktop
Classifier: Topic :: Office/Business :: Office Suites
Classifier: Topic :: Text Processing :: General
Classifier: License :: OSI Approved :: MIT License
Classifier: Programming Language :: Python :: 3
Classifier: Programming Language :: Python :: 3.8
Classifier: Programming Language :: Python :: 3.9
Classifier: Programming Language :: Python :: 3.10
Classifier: Programming Language :: Python :: 3.11
Classifier: Programming Language :: Python :: 3.12
Classifier: Operating System :: OS Independent
Classifier: Environment :: Console
Requires-Python: >=3.8
License-File: LICENSE
Requires-Dist: typer>=0.9.0
Requires-Dist: requests>=2.28.0
Requires-Dist: numpy>=1.21.0
Requires-Dist: sentence-transformers>=2.2.0
Requires-Dist: python-dotenv>=0.19.0
Requires-Dist: PyMuPDF>=1.20.0
Requires-Dist: python-docx>=0.8.11
Requires-Dist: torch>=1.12.0
Requires-Dist: transformers>=4.20.0
Dynamic: author
Dynamic: author-email
Dynamic: classifier
Dynamic: description
Dynamic: description-content-type
Dynamic: home-page
Dynamic: keywords
Dynamic: license
Dynamic: license-file
Dynamic: project-url
Dynamic: requires-dist
Dynamic: requires-python
Dynamic: summary
